[
  {
    "id": "tr-001",
    "description": "Transaction 1",
    "amount": 3984.62,
    "status": "paid",
    "date": "2026-04-28",
    "category": "infra"
  },
  {
    "id": "tr-002",
    "description": "Transaction 2",
    "amount": 4218.73,
    "status": "pending",
    "date": "2026-04-29",
    "category": "payroll"
  },
  {
    "id": "tr-003",
    "description": "Transaction 3",
    "amount": 1629.77,
    "status": "failed",
    "date": "2026-04-30",
    "category": "ops"
  },
  {
    "id": "tr-004",
    "description": "Transaction 4",
    "amount": 4127.86,
    "status": "paid",
    "date": "2026-05-01",
    "category": "taxes"
  },
  {
    "id": "tr-005",
    "description": "Transaction 5",
    "amount": 5470.33,
    "status": "pending",
    "date": "2026-05-02",
    "category": "services"
  },
  {
    "id": "tr-006",
    "description": "Transaction 6",
    "amount": 7562.27,
    "status": "failed",
    "date": "2026-05-03",
    "category": "infra"
  },
  {
    "id": "tr-007",
    "description": "Transaction 7",
    "amount": 1744.31,
    "status": "paid",
    "date": "2026-05-04",
    "category": "payroll"
  },
  {
    "id": "tr-008",
    "description": "Transaction 8",
    "amount": 7542.13,
    "status": "pending",
    "date": "2026-05-05",
    "category": "ops"
  },
  {
    "id": "tr-009",
    "description": "Transaction 9",
    "amount": 5021.85,
    "status": "failed",
    "date": "2026-05-06",
    "category": "taxes"
  },
  {
    "id": "tr-010",
    "description": "Transaction 10",
    "amount": 3945.38,
    "status": "paid",
    "date": "2026-05-07",
    "category": "services"
  },
  {
    "id": "tr-011",
    "description": "Transaction 11",
    "amount": 3567.48,
    "status": "pending",
    "date": "2026-05-08",
    "category": "infra"
  },
  {
    "id": "tr-012",
    "description": "Transaction 12",
    "amount": 6664.48,
    "status": "failed",
    "date": "2026-05-09",
    "category": "payroll"
  },
  {
    "id": "tr-013",
    "description": "Transaction 13",
    "amount": 5407.75,
    "status": "paid",
    "date": "2026-05-10",
    "category": "ops"
  },
  {
    "id": "tr-014",
    "description": "Transaction 14",
    "amount": 2805.77,
    "status": "pending",
    "date": "2026-05-11",
    "category": "taxes"
  },
  {
    "id": "tr-015",
    "description": "Transaction 15",
    "amount": 6162.63,
    "status": "failed",
    "date": "2026-05-12",
    "category": "services"
  },
  {
    "id": "tr-016",
    "description": "Transaction 16",
    "amount": 6975.98,
    "status": "paid",
    "date": "2026-05-13",
    "category": "infra"
  },
  {
    "id": "tr-017",
    "description": "Transaction 17",
    "amount": 4666.42,
    "status": "pending",
    "date": "2026-05-14",
    "category": "payroll"
  },
  {
    "id": "tr-018",
    "description": "Transaction 18",
    "amount": 5001.65,
    "status": "failed",
    "date": "2026-05-15",
    "category": "ops"
  },
  {
    "id": "tr-019",
    "description": "Transaction 19",
    "amount": 1883.32,
    "status": "paid",
    "date": "2026-05-16",
    "category": "taxes"
  },
  {
    "id": "tr-020",
    "description": "Transaction 20",
    "amount": 2285.71,
    "status": "pending",
    "date": "2026-05-17",
    "category": "services"
  },
  {
    "id": "tr-021",
    "description": "Transaction 21",
    "amount": 7260.44,
    "status": "failed",
    "date": "2026-05-18",
    "category": "infra"
  },
  {
    "id": "tr-022",
    "description": "Transaction 22",
    "amount": 9665.35,
    "status": "paid",
    "date": "2026-05-19",
    "category": "payroll"
  },
  {
    "id": "tr-023",
    "description": "Transaction 23",
    "amount": 6817.74,
    "status": "pending",
    "date": "2026-05-20",
    "category": "ops"
  },
  {
    "id": "tr-024",
    "description": "Transaction 24",
    "amount": 4621.9,
    "status": "failed",
    "date": "2026-05-21",
    "category": "taxes"
  },
  {
    "id": "tr-025",
    "description": "Transaction 25",
    "amount": 7061.85,
    "status": "paid",
    "date": "2026-05-22",
    "category": "services"
  },
  {
    "id": "tr-026",
    "description": "Transaction 26",
    "amount": 2584.43,
    "status": "pending",
    "date": "2026-05-23",
    "category": "infra"
  },
  {
    "id": "tr-027",
    "description": "Transaction 27",
    "amount": 9001.38,
    "status": "failed",
    "date": "2026-05-24",
    "category": "payroll"
  },
  {
    "id": "tr-028",
    "description": "Transaction 28",
    "amount": 1900.75,
    "status": "paid",
    "date": "2026-05-25",
    "category": "ops"
  },
  {
    "id": "tr-029",
    "description": "Transaction 29",
    "amount": 4333.83,
    "status": "pending",
    "date": "2026-05-26",
    "category": "taxes"
  },
  {
    "id": "tr-030",
    "description": "Transaction 30",
    "amount": 6773.76,
    "status": "failed",
    "date": "2026-05-27",
    "category": "services"
  },
  {
    "id": "tr-031",
    "description": "Transaction 31",
    "amount": 6645.64,
    "status": "paid",
    "date": "2026-05-28",
    "category": "infra"
  },
  {
    "id": "tr-032",
    "description": "Transaction 32",
    "amount": 5635.19,
    "status": "pending",
    "date": "2026-05-29",
    "category": "payroll"
  },
  {
    "id": "tr-033",
    "description": "Transaction 33",
    "amount": 9954.22,
    "status": "failed",
    "date": "2026-05-30",
    "category": "ops"
  },
  {
    "id": "tr-034",
    "description": "Transaction 34",
    "amount": 3639.83,
    "status": "paid",
    "date": "2026-05-31",
    "category": "taxes"
  },
  {
    "id": "tr-035",
    "description": "Transaction 35",
    "amount": 3834.91,
    "status": "pending",
    "date": "2026-06-01",
    "category": "services"
  },
  {
    "id": "tr-036",
    "description": "Transaction 36",
    "amount": 1853.03,
    "status": "failed",
    "date": "2026-06-02",
    "category": "infra"
  },
  {
    "id": "tr-037",
    "description": "Transaction 37",
    "amount": 8848.73,
    "status": "paid",
    "date": "2026-06-03",
    "category": "payroll"
  },
  {
    "id": "tr-038",
    "description": "Transaction 38",
    "amount": 2845.93,
    "status": "pending",
    "date": "2026-06-04",
    "category": "ops"
  },
  {
    "id": "tr-039",
    "description": "Transaction 39",
    "amount": 9175.21,
    "status": "failed",
    "date": "2026-06-05",
    "category": "taxes"
  },
  {
    "id": "tr-040",
    "description": "Transaction 40",
    "amount": 7879.54,
    "status": "paid",
    "date": "2026-06-06",
    "category": "services"
  },
  {
    "id": "tr-041",
    "description": "Transaction 41",
    "amount": 4784.38,
    "status": "pending",
    "date": "2026-06-07",
    "category": "infra"
  },
  {
    "id": "tr-042",
    "description": "Transaction 42",
    "amount": 9769.71,
    "status": "failed",
    "date": "2026-06-08",
    "category": "payroll"
  },
  {
    "id": "tr-043",
    "description": "Transaction 43",
    "amount": 6433.62,
    "status": "paid",
    "date": "2026-06-09",
    "category": "ops"
  },
  {
    "id": "tr-044",
    "description": "Transaction 44",
    "amount": 8387.41,
    "status": "pending",
    "date": "2026-06-10",
    "category": "taxes"
  },
  {
    "id": "tr-045",
    "description": "Transaction 45",
    "amount": 3799.04,
    "status": "failed",
    "date": "2026-06-11",
    "category": "services"
  },
  {
    "id": "tr-046",
    "description": "Transaction 46",
    "amount": 1760.2,
    "status": "paid",
    "date": "2026-06-12",
    "category": "infra"
  },
  {
    "id": "tr-047",
    "description": "Transaction 47",
    "amount": 3944.48,
    "status": "pending",
    "date": "2026-06-13",
    "category": "payroll"
  },
  {
    "id": "tr-048",
    "description": "Transaction 48",
    "amount": 1223.47,
    "status": "failed",
    "date": "2026-06-14",
    "category": "ops"
  },
  {
    "id": "tr-049",
    "description": "Transaction 49",
    "amount": 5045.6,
    "status": "paid",
    "date": "2026-06-15",
    "category": "taxes"
  },
  {
    "id": "tr-050",
    "description": "Transaction 50",
    "amount": 2728.8,
    "status": "pending",
    "date": "2026-06-16",
    "category": "services"
  }
]
